{
  "信じて、見つけるから\r\n": "Поверь, и я обязательно найду ",
  "ああ毎秒うつむけばため息 \r\n": "Ах, стоит мне опустить голову — и каждую секунду вырывается вздох",
  "鏡の中で僕はどんな顔してるの？ \r\n": "Какое у меня сейчас лицо в зеркале?",
  "見えなくてさ\r\n": "Я его не вижу, знаешь",
  "舞台の外側がまだ怖くて\r\n": "Мне всё ещё страшно за пределами сцены",
  "<size=37>崖の向こうで聴こえてる声の方へ駆け寄れないでいたんだ</size>\r\n": "Я всё не мог заставить себя броситься к голосу, что слышался по ту сторону обрыва",
  "限りないキラめき／暗闇\r\n": "Бесконечное сияние/тьма",
  "あざ笑う爪先\r\n": "насмешливые кончики пальцев ног",
  "それでもまだ君が期待した光が僕に射すから\r\n": "Но даже так свет, на который ты возлагал(а) надежды, всё ещё падает на меня",
  "いつか世界の果てまでこの歌が届くなら\r\n": "Если однажды эта песня дойдёт до самого края мира,",
  "たとえどんな痛みが待ち受けていようと進もう\r\n": "я пойду вперёд, какой бы боль ни ждала меня там",
  "さあ目を開いて\r\n": "Ну же, открой глаза",
  "（僕が選んだ色自体が僕だ）\r\n": "(Цвет, который я выбрал для себя, и есть я сам)",
  "望むなら届くから\r\n": "Если желать, оно дойдёт",
  "（誰にも剥がせない）\r\n": "(Этого никому не содрать)",
  "（The Choice is just mine）\r\n": "(The Choice is just mine)",
  "遠く彼方、一番星(トップスター)でさえ\r\n": "Даже до самой далёкой первой звезды(top star)",
  "僕はずっと、夢を見ていた\r\n": "я всё это время мечтал",
  "瞼の外側で、まだ消えないで、\r\n": "По ту сторону век, не исчезай ещё,",
  "それは僕に瞬いたから\r\n": "ведь это сияние вспыхнуло для меня",
  "変わらない数字を嘆くのをやめた時気付けた\r\n": "Когда я перестал оплакивать неизменные цифры, я понял",
  "弱くても初めから手にしてたフォーカード\r\n": "Пусть он и слабый, но four-of-a-kind с самого начала был у меня в руках",
  "逆さまの夢の続きを\r\n": "Продолжение перевёрнутой мечты",
  "君と\r\n": "вместе с тобой",
  "いま世界の果てまでこの歌が繋げるから\r\n": "Сейчас эта песня соединит даже самые дальние края мира",
  "きっと世界の果てまでこの歌は届くから\r\n": "Эта песня точно дойдёт до самых дальних краёв мира",
  "抱いていた光が涙に濡れても連れて行こう \r\n": "Даже если свет, что я держал, промок от слёз, я всё равно понесу его с собой",
  "だから目を開いて\r\n": "Поэтому открой глаза",
  "孤独じゃないよ、僕らは\r\n": "Мы не одиноки, мы "
}
