{
    "help-achievement|achievement-achievement|1|name": "Achievements",
    "help-achievement|achievement-idol|2|name": "Idol Achievements",
    "help-achievement|achievement-others|4|name": "Other Achievements",
    "help-achievement|achievement-produce-achievement|3|name": "Produce Achievements",
    "help-box-gasha-event|box-gasha-event|1|name": "Seasonal Events",
    "help-box-gasha-event|box-gasha-event-bonus|3|name": "Event Bonuses",
    "help-box-gasha-event|box-gasha-event-finish|8|name": "After the Event",
    "help-box-gasha-event|box-gasha-event-gasha|4|name": "Event Gacha",
    "help-box-gasha-event|box-gasha-event-gasha-coin|7|name": "Event Items",
    "help-box-gasha-event|box-gasha-event-idol|2|name": "Event Rewards Produce Idol",
    "help-box-gasha-event|box-gasha-event-mission|6|name": "Event Missions",
    "help-box-gasha-event|box-gasha-event-story|5|name": "Event Commu",
    "help-circle-battle-event|circle-battle-event-exchange|5|name": "Regional Tour Medals",
    "help-circle-battle-event|circle-battle-event-finish|9|name": "After the Event",
    "help-circle-battle-event|circle-battle-event-memory|3|name": "Formation",
    "help-circle-battle-event|circle-battle-event-mission|7|name": "Event Missions",
    "help-circle-battle-event|circle-battle-event-ranking|8|name": "Circle Rankings",
    "help-circle-battle-event|circle-battle-event-reward|4|name": "Event Rewards",
    "help-circle-battle-event|circle-battle-event-rule|1|name": "Regional Tour Events",
    "help-circle-battle-event|circle-battle-event-stage|2|name": "Stages",
    "help-circle-battle-event|circle-battle-event-story|6|name": "Event Commu",
    "help-contest|contest-contest|1|name": "Contests",
    "help-contest|contest-contest-ranking|10|name": "Contest Rankings",
    "help-contest|contest-grade|8|name": "Grades",
    "help-contest|contest-preparation-period|7|name": "Preparation Period",
    "help-contest|contest-rate-pt|9|name": "Rate Points",
    "help-contest|contest-rule|2|name": "Contest Rules",
    "help-contest|contest-season|6|name": "Seasons",
    "help-contest|contest-squad|3|name": "Formation",
    "help-contest|contest-stage|4|name": "Stages",
    "help-contest|contest-total|5|name": "Total Strength",
    "help-event_mission|event_mission-event_mission|1|name": "Event Missions",
    "help-event-mission|event-mission-rookie|1|name": "Daily Unlock Missions",
    "help-gasha|gasha-Gasha|1|name": "Gacha",
    "help-gasha|gasha-gasha-pt|2|name": "Exchange Points and Flowers",
    "help-guild|guild-create|2|name": "Circle Creation",
    "help-guild|guild-Guild|1|name": "Circles",
    "help-guild|guild-join|3|name": "Joining a Circle",
    "help-guild|guild-leave|6|name": "Leaving/Expelling from a Circle",
    "help-guild|guild-message-board|4|name": "Message Board",
    "help-guild|guild-request|5|name": "Requests",
    "help-highscore|highscore-highscore|1|name": "Overview of Kunio Juo's Idol Growth Month",
    "help-highscore|highscore-ranking|2|name": "High Score Ranking Types",
    "help-highscore|highscore-score_reward|3|name": "High Score Achievement Rewards",
    "help-home|home-ap|3|name": "AP",
    "help-home|home-day-reset|9|name": "Date Reset",
    "help-home|home-home|1|name": "Home",
    "help-home|home-home-character-change|7|name": "Home Idol Settings",
    "help-home|home-jewel|4|name": "Jewels",
    "help-home|home-main-task|8|name": "Challenges",
    "help-home|home-money-received|5|name": "Activity Funds",
    "help-home|home-p-lv|2|name": "Producer Level",
    "help-home|home-work|6|name": "Jobs",
    "help-idol|idol-another|2|name": "Another Idol",
    "help-idol|idol-dearness|53|name": "Bond",
    "help-idol|idol-idol-card|1|name": "Produce Idol",
    "help-idol|idol-idol-card-level-limit|50|name": "Training",
    "help-idol|idol-idol-card-potential-rank|51|name": "Talent Bloom",
    "help-idol|idol-idol-card-release|52|name": "Unlocking Produce Idol",
    "help-idol|idol-parameter|3|name": "Parameters",
    "help-idol|idol-plan1|20|name": "Plan: Sense",
    "help-idol|idol-plan2|30|name": "Plan: Logic",
    "help-idol|idol-plan3|40|name": "Plan: Anomaly",
    "help-idol|idol-true-end-bonus|54|name": "True End Bonus",
    "help-lesson|lesson-audition|15|name": "Exams",
    "help-lesson|lesson-audition-flow|16|name": "Exam Flow",
    "help-lesson|lesson-audition-view|17|name": "Exam Display",
    "help-lesson|lesson-block|4|name": "Energy",
    "help-lesson|lesson-effect|12|name": "Triggered Effects",
    "help-lesson|lesson-gimmick|13|name": "Support and Troubles",
    "help-lesson|lesson-health-lesson|3|name": "Stamina (Lessons)",
    "help-lesson|lesson-lesson|1|name": "Lessons",
    "help-lesson|lesson-lesson-view|2|name": "Lesson Display",
    "help-lesson|lesson-p-drink|9|name": "P-Items",
    "help-lesson|lesson-p-item|8|name": "P-Drinks",
    "help-lesson|lesson-perfect-lesson|14|name": "Perfect Lessons",
    "help-lesson|lesson-produce-card|5|name": "Skill Cards",
    "help-lesson|lesson-produce-card-powerup|6|name": "Skill Card Enhancement",
    "help-lesson|lesson-produce-card-use|7|name": "Skill Card Usage Procedure",
    "help-lesson|lesson-skip|10|name": "SKIP",
    "help-lesson|lesson-support|11|name": "Skill Card Support",
    "help-main-story-event|help-main-story-event-bonus|4|name": "Event Bonuses",
    "help-main-story-event|help-main-story-event-coin|6|name": "Event Exchange Items",
    "help-main-story-event|help-main-story-event-finish|7|name": "After the Event",
    "help-main-story-event|help-main-story-event-main-story|3|name": "Unlocking Hatsuboshi Commu",
    "help-main-story-event|help-main-story-event-mission|2|name": "Event Missions",
    "help-main-story-event|help-main-story-event-point|5|name": "Cumulative Event Points Rewards",
    "help-main-story-event|help-main-story-event-story|1|name": "Hatsuboshi Commu Events",
    "help-memory|memory-memory|1|name": "Memories",
    "help-memory|memory-memory-contest|3|name": "Effects During Contest Formation",
    "help-memory|memory-memory-convert|5|name": "Memory Conversion",
    "help-memory|memory-memory-deck-edit|4|name": "Memory Formation Screen",
    "help-memory|memory-memory-inherit|6|name": "Memory Synthesis",
    "help-memory|memory-memory-produce|2|name": "Effects During Produce Formation",
    "help-menu|menu-album-to-live|9|name": "Photo Album",
    "help-menu|menu-costume|7|name": "Outfits",
    "help-menu|menu-data-linkage|17|name": "Data Linking",
    "help-menu|menu-friend|2|name": "Friends",
    "help-menu|menu-friend-invite|3|name": "Friend Invitation Feature",
    "help-menu|menu-help|13|name": "Help",
    "help-menu|menu-item|5|name": "Inventory",
    "help-menu|menu-live-shooting|8|name": "Photography",
    "help-menu|menu-media|12|name": "Media",
    "help-menu|menu-meishi|4|name": "Business Cards",
    "help-menu|menu-music|10|name": "Music",
    "help-menu|menu-predownload|16|name": "Batch Download",
    "help-menu|menu-produce-collection|6|name": "P-Encyclopedia",
    "help-menu|menu-profile|1|name": "Profile",
    "help-menu|menu-roster|11|name": "Roster",
    "help-menu|menu-setting|14|name": "Settings",
    "help-menu|menu-title|15|name": "Title",
    "help-mission|mission-daily|2|name": "Daily Missions",
    "help-mission|mission-event|6|name": "Event Missions",
    "help-mission|mission-mission|1|name": "Missions",
    "help-mission|mission-normal|4|name": "Normal Missions",
    "help-mission|mission-pass|7|name": "Mission Pass",
    "help-mission|mission-special|5|name": "Limited-Time Missions",
    "help-mission|mission-weekly|3|name": "Weekly Missions",
    "help-panel-mission|panel-mission-panel-mission|1|name": "Panel Missions",
    "help-produce|produce-003-add|37|name": "Difficulty: Master",
    "help-produce|produce-business|40|name": "Business Operations",
    "help-produce|produce-character-growth|13|name": "Training Goals",
    "help-produce|produce-confirm|8|name": "Start Confirmation Screen",
    "help-produce|produce-costume-choice|3|name": "Costume Selection",
    "help-produce|produce-customize|42|name": "Special Guidance",
    "help-produce|produce-customize-customize|43|name": "Skill Card Customization",
    "help-produce|produce-ending|29|name": "Ending",
    "help-produce|produce-event|22|name": "Idol Commu (Produce)",
    "help-produce|produce-exam-audition|27|name": "Exams (Produce)",
    "help-produce|produce-fanpresent|44|name": "Refreshments",
    "help-produce|produce-fanvote|39|name": "Fan Votes",
    "help-produce|produce-generate-memory|32|name": "Memory Creation",
    "help-produce|produce-growth-info|4|name": "Training Info",
    "help-produce|produce-hard-lesson|26|name": "Intensive Lessons",
    "help-produce|produce-health-produce|14|name": "Stamina (Produce)",
    "help-produce|produce-idol-card-select|2|name": "Produce Idol Selection",
    "help-produce|produce-judging-trend|10|name": "Evaluation Criteria",
    "help-produce|produce-lesson|24|name": "Lessons (Produce)",
    "help-produce|produce-live|28|name": "P-Lives",
    "help-produce|produce-memory-deck-edit|7|name": "Memory Formation (Produce)",
    "help-produce|produce-menu|33|name": "Menu",
    "help-produce|produce-nia_audition|45|name": "Auditions",
    "help-produce|produce-ppoint|18|name": "P-Points",
    "help-produce|produce-present|21|name": "Activity Support",
    "help-produce|produce-produce|1|name": "Produce",
    "help-produce|produce-produce-1|34|name": "Regular Performance \"Hajime\"",
    "help-produce|produce-produce-2|38|name": "NEXT IDOL AUDITION",
    "help-produce|produce-produce-drink|16|name": "P-Drinks",
    "help-produce|produce-produce-item|17|name": "P-Items",
    "help-produce|produce-produce-ranking|35|name": "Produce Rankings",
    "help-produce|produce-ProduceSchedule|11|name": "P-Book",
    "help-produce|produce-refresh|15|name": "Rest",
    "help-produce|produce-result|31|name": "Produce Results",
    "help-produce|produce-schedule-confirm|12|name": "Schedule",
    "help-produce|produce-schedule-select|9|name": "Schedule Selection",
    "help-produce|produce-select-info|5|name": "Formation Details",
    "help-produce|produce-self_lesson|41|name": "Self-Lessons",
    "help-produce|produce-seminar|36|name": "Training",
    "help-produce|produce-shool-actibity|20|name": "Lessons/Outings",
    "help-produce|produce-shop|19|name": "Consultations",
    "help-produce|produce-sp-lesson|25|name": "SP-Lessons",
    "help-produce|produce-support-card-deck-edit|6|name": "Support Card Formation (Produce)",
    "help-produce|produce-support-event|23|name": "Support Card Events",
    "help-produce|produce-true-end|30|name": "True End: \"Hajime\"",
    "help-produce|produce-true-end-2|46|name": "True End: N.I.A",
    "help-shop|shop-coingasha|5|name": "Coin Gacha",
    "help-shop|shop-costume|9|name": "Costume Shop",
    "help-shop|shop-exchange|7|name": "Item Exchange",
    "help-shop|shop-exchange-daily|6|name": "Daily Exchange",
    "help-shop|shop-exchange-ticket|8|name": "Ticket Exchange",
    "help-shop|shop-itemshop|3|name": "Packs",
    "help-shop|shop-jewel|2|name": "Jewels",
    "help-shop|shop-mission-pass|4|name": "Passes",
    "help-shop|shop-shop-all|1|name": "Shop",
    "help-story|story-story|1|name": "Commu",
    "help-story|story-story-event-story|5|name": "Event Commu",
    "help-story|story-story-idol|3|name": "Idol Commu",
    "help-story|story-story-main|2|name": "Hatsuboshi Commu",
    "help-story|story-story-support-card|4|name": "Support Commu",
    "help-story-event|story-event-event-coin|6|name": "Event Exchange Items",
    "help-story-event|story-event-event-finish|7|name": "After the Event",
    "help-story-event|story-event-event-mission|5|name": "Event Missions",
    "help-story-event|story-event-event-point|3|name": "Cumulative Event Points Rewards",
    "help-story-event|story-event-event-story|1|name": "Story Events",
    "help-story-event|story-event-event-story-bonus|2|name": "Event Bonuses",
    "help-story-event|story-event-event-story-story-unlock|4|name": "Event Commu",
    "help-story-event-guild-mission|guild-mission|1|name": "Linked Missions",
    "help-support|support-lesson-support|2|name": "Skill Card Support",
    "help-support|support-produce-upgrade-select|5|name": "Level Enhancement",
    "help-support|support-support-ability|4|name": "Support Abilities",
    "help-support|support-support-bonus|9|name": "Support Bonuses",
    "help-support|support-support-card|1|name": "Support Cards",
    "help-support|support-support-card-deck-edit|7|name": "Support Card Formation",
    "help-support|support-support-card-exchange|8|name": "Support Conversion",
    "help-support|support-support-card-level-limit-rank|6|name": "Limit Break",
    "help-support|support-support-event|3|name": "Support Events",
    "help-tower|clear-rank|3|name": "Clear Condition Stars",
    "help-tower|memory-memory-tower|4|name": "Memory Formation for Idol Road",
    "help-tower|tower|1|name": "Idol Road",
    "help-tower|tower-achivement|5|name": "Idol Road Achievements",
    "help-tower|tower-rule|2|name": "Rules for Idol Road"
}