{
  "data": [
    {
      "number": 1,
      "supportCardId": "s_card-2-0000",
      "text": "Big sis, found you!!"
    },
    {
      "number": 2,
      "supportCardId": "s_card-2-0000",
      "text": "Whoa!!\nHey... That’s dangerous, Ume!!"
    },
    {
      "number": 3,
      "supportCardId": "s_card-2-0000",
      "text": "Hehe, it’s an ultra loving glomp~!"
    },
    {
      "number": 1,
      "supportCardId": "s_card-2-0001",
      "text": "......"
    },
    {
      "number": 2,
      "supportCardId": "s_card-2-0001",
      "text": "......"
    },
    {
      "number": 1,
      "supportCardId": "s_card-2-0002",
      "text": "Kotone, today for sure..."
    },
    {
      "number": 2,
      "supportCardId": "s_card-2-0002",
      "text": "Ack... Excuse meee!!"
    },
    {
      "number": 3,
      "supportCardId": "s_card-2-0002",
      "text": "Ah!\n...Geez, what a troublesome junior."
    },
    {
      "number": 1,
      "supportCardId": "s_card-2-0003",
      "text": "Sorry for making you study with me."
    },
    {
      "number": 2,
      "supportCardId": "s_card-2-0003",
      "text": "No, we help each other when in trouble,\nright?"
    },
    {
      "number": 3,
      "supportCardId": "s_card-2-0003",
      "text": "Haha, I always rely on you."
    },
    {
      "number": 1,
      "supportCardId": "s_card-2-0004",
      "text": "Your left hand like this... straight, okay?"
    },
    {
      "number": 2,
      "supportCardId": "s_card-2-0004",
      "text": "S-straight! Like this!?"
    },
    {
      "number": 3,
      "supportCardId": "s_card-2-0004",
      "text": "Yes, straight!\nHaha, you’re getting it, you’re getting it."
    },
    {
      "number": 1,
      "supportCardId": "s_card-2-0005",
      "text": "Hehe, you fell for it again~♪"
    },
    {
      "number": 2,
      "supportCardId": "s_card-2-0005",
      "text": "S-Sumika-chan...!"
    },
    {
      "number": 3,
      "supportCardId": "s_card-2-0005",
      "text": "......H-Hey! Always pranking me..."
    },
    {
      "number": 1,
      "supportCardId": "s_card-2-0006",
      "text": "Nice muscles! What kind of training\ndo you do?"
    },
    {
      "number": 2,
      "supportCardId": "s_card-2-0006",
      "text": "I’ll share my regimen, so tell me about\nyours, Sumika."
    },
    {
      "number": 3,
      "supportCardId": "s_card-2-0006",
      "text": "Ahh, I don’t work out or anything,\nso I’m good~."
    },
    {
      "number": 1,
      "supportCardId": "s_card-2-0007",
      "text": "Whew~."
    },
    {
      "number": 2,
      "supportCardId": "s_card-2-0007",
      "text": "Wow! So beautiful!\nShinosawa-san, you’re amazing!"
    },
    {
      "number": 3,
      "supportCardId": "s_card-2-0007",
      "text": "...Haha. China, do you want to try?"
    },
    {
      "number": 1,
      "supportCardId": "s_card-2-0008",
      "text": "Oh, you seem tense again."
    },
    {
      "number": 2,
      "supportCardId": "s_card-2-0008",
      "text": "Whaaa! Se-Sena-Oneesama...\nYou didn’t see that, did you!?"
    },
    {
      "number": 3,
      "supportCardId": "s_card-2-0008",
      "text": "(Ughh... This is too much,\nI’m happy and embarrassed!)"
    },
    {
      "number": 1,
      "supportCardId": "s_card-2-0009",
      "text": "Mm-mm... Puh-ha!!"
    },
    {
      "number": 2,
      "supportCardId": "s_card-2-0009",
      "text": "(Wait, she chugged it?\nSomething that tastes this bad!?)"
    },
    {
      "number": 3,
      "supportCardId": "s_card-2-0009",
      "text": "(Unbelievable...!)"
    },
    {
      "number": 1,
      "supportCardId": "s_card-2-0010",
      "text": "It’s so warm...\nPerfect for a nap."
    },
    {
      "number": 2,
      "supportCardId": "s_card-2-0010",
      "text": "Mmm, hmm... snooze..."
    },
    {
      "number": 3,
      "supportCardId": "s_card-2-0010",
      "text": "...Haha. I’ll join you."
    },
    {
      "number": 1,
      "supportCardId": "s_card-2-0011",
      "text": "Kotone, you really know how to present\nyourself."
    },
    {
      "number": 2,
      "supportCardId": "s_card-2-0011",
      "text": "You truly should belong to me."
    },
    {
      "number": 3,
      "supportCardId": "s_card-2-0011",
      "text": "Ahaha... It’s an honor."
    },
    {
      "number": 1,
      "supportCardId": "s_card-2-0012",
      "text": "Here, have some water."
    },
    {
      "number": 2,
      "supportCardId": "s_card-2-0012",
      "text": "You’re a lifesaver... My hero."
    },
    {
      "number": 3,
      "supportCardId": "s_card-2-0012",
      "text": "Take it slow, no rush."
    },
    {
      "number": 1,
      "supportCardId": "s_card-2-0013",
      "text": "Here, the petal’s off."
    },
    {
      "number": 2,
      "supportCardId": "s_card-2-0013",
      "text": "...Hm? Oh, thanks."
    },
    {
      "number": 3,
      "supportCardId": "s_card-2-0013",
      "text": "...These little moments,\njust one more year."
    },
    {
      "number": 1,
      "supportCardId": "s_card-2-0014",
      "text": "So far, so good?"
    },
    {
      "number": 2,
      "supportCardId": "s_card-2-0014",
      "text": "If you have questions,\ndon’t hesitate to ask."
    },
    {
      "number": 3,
      "supportCardId": "s_card-2-0014",
      "text": "No need to hold back with the teacher."
    },
    {
      "number": 1,
      "supportCardId": "s_card-2-0015",
      "text": "What are you listening to, Temari-chan?"
    },
    {
      "number": 2,
      "supportCardId": "s_card-2-0015",
      "text": "Ah, hey...!\nDon't touch without permission!"
    },
    {
      "number": 1,
      "supportCardId": "s_card-2-0016",
      "text": "Take this!"
    },
    {
      "number": 2,
      "supportCardId": "s_card-2-0016",
      "text": "Yikes!!"
    },
    {
      "number": 1,
      "supportCardId": "s_card-2-0018",
      "text": "Wait, is it already over?"
    },
    {
      "number": 2,
      "supportCardId": "s_card-2-0018",
      "text": "Grr...!"
    },
    {
      "number": 3,
      "supportCardId": "s_card-2-0018",
      "text": "Not yet!"
    },
    {
      "number": 1,
      "supportCardId": "s_card-2-0019",
      "text": "Here we go, strike a pose!"
    },
    {
      "number": 2,
      "supportCardId": "s_card-2-0019",
      "text": "Huh?"
    },
    {
      "number": 3,
      "supportCardId": "s_card-2-0019",
      "text": "Oh! Whoa!"
    },
    {
      "number": 1,
      "supportCardId": "s_card-2-0020",
      "text": "Hehe, feeling uneasy in a swimsuit?"
    },
    {
      "number": 2,
      "supportCardId": "s_card-2-0020",
      "text": "Is the swimsuit weird?"
    },
    {
      "number": 3,
      "supportCardId": "s_card-2-0020",
      "text": "It's super cute!"
    },
    {
      "number": 1,
      "supportCardId": "s_card-2-0021",
      "text": "Ahhh... Ahhh..."
    },
    {
      "number": 2,
      "supportCardId": "s_card-2-0021",
      "text": "How's this? An alien's voice."
    },
    {
      "number": 3,
      "supportCardId": "s_card-2-0021",
      "text": "You're such an idiot."
    },
    {
      "number": 1,
      "supportCardId": "s_card-2-0023",
      "text": "—Here, hop on my back."
    },
    {
      "number": 2,
      "supportCardId": "s_card-2-0023",
      "text": "Don't worry, it's fine."
    },
    {
      "number": 3,
      "supportCardId": "s_card-2-0023",
      "text": "Ugh... Mao-senpai's back is so warm..."
    },
    {
      "number": 1,
      "supportCardId": "s_card-2-0024",
      "text": "Like this, and this! Got it!"
    },
    {
      "number": 2,
      "supportCardId": "s_card-2-0024",
      "text": "Chinacchi, you're amazing~♪"
    },
    {
      "number": 3,
      "supportCardId": "s_card-2-0024",
      "text": "Tightening not just the obi but also the\nwaist cord is the trick."
    },
    {
      "number": 1,
      "supportCardId": "s_card-2-0025",
      "text": "I feel Kotone’s presence somehow."
    },
    {
      "number": 2,
      "supportCardId": "s_card-2-0025",
      "text": "The cotton candy mask shouldn’t give\nme away!"
    },
    {
      "number": 3,
      "supportCardId": "s_card-2-0025",
      "text": "Hehe—I can see you."
    },
    {
      "number": 1,
      "supportCardId": "s_card-2-0027",
      "text": "How’s this year’s batch of freshmen?"
    },
    {
      "number": 2,
      "supportCardId": "s_card-2-0027",
      "text": "Hehe, full of diamonds in the rough."
    },
    {
      "number": 3,
      "supportCardId": "s_card-2-0027",
      "text": "That’s exciting."
    },
    {
      "number": 1,
      "supportCardId": "s_card-2-0028",
      "text": "Kotone-chan, your pampas grass is\nreally impressive!"
    },
    {
      "number": 2,
      "supportCardId": "s_card-2-0028",
      "text": "Wow, thank you so much!"
    },
    {
      "number": 3,
      "supportCardId": "s_card-2-0028",
      "text": "......Wait, are we playing?!"
    },
    {
      "number": 1,
      "supportCardId": "s_card-2-0029",
      "text": "Acting... is so hard."
    },
    {
      "number": 2,
      "supportCardId": "s_card-2-0029",
      "text": "Tsukimura-san’s personality is very\nweird, you know."
    },
    {
      "number": 3,
      "supportCardId": "s_card-2-0029",
      "text": "Tell me more!"
    },
    {
      "number": 1,
      "supportCardId": "s_card-2-0030",
      "text": "That drink looks interesting."
    },
    {
      "number": 2,
      "supportCardId": "s_card-2-0030",
      "text": "Hehe~ You’ve got good eyes."
    },
    {
      "number": 3,
      "supportCardId": "s_card-2-0030",
      "text": "What did you mix to get that color?\nSo mysterious."
    },
    {
      "number": 1,
      "supportCardId": "s_card-2-0031",
      "text": "I saw it the other day..."
    },
    {
      "number": 2,
      "supportCardId": "s_card-2-0031",
      "text": "My sister’s secret drink recipe.\nWhisper whisper..."
    },
    {
      "number": 3,
      "supportCardId": "s_card-2-0031",
      "text": "Whattt!?"
    },
    {
      "number": 1,
      "supportCardId": "s_card-2-0032",
      "text": "Waving a fan like this ensures even\nroasting!"
    },
    {
      "number": 2,
      "supportCardId": "s_card-2-0032",
      "text": "I see... This is for better heat distribution."
    },
    {
      "number": 3,
      "supportCardId": "s_card-2-0032",
      "text": "This also prevents a smoky smell and\nenhances the aroma!"
    },
    {
      "number": 1,
      "supportCardId": "s_card-2-0033",
      "text": "Mao-senpai, your expression is stiff!\nMore! Smile more!"
    },
    {
      "number": 2,
      "supportCardId": "s_card-2-0033",
      "text": "L-Like this?\nI’m not used to this sort of thing."
    },
    {
      "number": 3,
      "supportCardId": "s_card-2-0033",
      "text": "Hmm, but even a worried Mao-senpai\nis cute, so it’s fine!"
    },
    {
      "number": 1,
      "supportCardId": "s_card-2-0034",
      "text": "Look, there’s a dragonfly!\nHow nostalgic."
    },
    {
      "number": 2,
      "supportCardId": "s_card-2-0034",
      "text": "Let’s see who catches the most, Ume!"
    },
    {
      "number": 3,
      "supportCardId": "s_card-2-0034",
      "text": "Alright! I won’t lose, Sis!"
    },
    {
      "number": 1,
      "supportCardId": "s_card-2-0035",
      "text": "Hohoho~"
    },
    {
      "number": 2,
      "supportCardId": "s_card-2-0035",
      "text": "I’ll deliver presents to good kids~."
    },
    {
      "number": 3,
      "supportCardId": "s_card-2-0035",
      "text": "Hehe~\nLeave it to Ume the reindeer!"
    },
    {
      "number": 1,
      "supportCardId": "s_card-2-0036",
      "text": "Rest your hand on your chin~\nand lift the corners of your mouth!"
    },
    {
      "number": 2,
      "supportCardId": "s_card-2-0036",
      "text": "L-Like this?"
    },
    {
      "number": 3,
      "supportCardId": "s_card-2-0036",
      "text": "Yup, yup! That’s perfect!"
    },
    {
      "number": 1,
      "supportCardId": "s_card-2-0037",
      "text": "How about splitting it in half?"
    },
    {
      "number": 2,
      "supportCardId": "s_card-2-0037",
      "text": "If you insist—chomp."
    },
    {
      "number": 3,
      "supportCardId": "s_card-2-0037",
      "text": "Your eyes are sparkling!\nYou’re so cute~!"
    },
    {
      "number": 1,
      "supportCardId": "s_card-3-0000",
      "text": "Here, have a bite!"
    },
    {
      "number": 2,
      "supportCardId": "s_card-3-0000",
      "text": "(...Can I eat this?)"
    },
    {
      "number": 3,
      "supportCardId": "s_card-3-0000",
      "text": "...No thanks."
    },
    {
      "number": 1,
      "supportCardId": "s_card-3-0001",
      "text": "(I hid instinctively...\nWhat am I even doing?)"
    },
    {
      "number": 2,
      "supportCardId": "s_card-3-0001",
      "text": "(It feels...\nnostalgic somehow...)"
    },
    {
      "number": 3,
      "supportCardId": "s_card-3-0001",
      "text": "(Let’s head toward the warmth...)"
    },
    {
      "number": 1,
      "supportCardId": "s_card-3-0002",
      "text": "I’ll never forgive you!!"
    },
    {
      "number": 2,
      "supportCardId": "s_card-3-0002",
      "text": "You don’t need to get that mad!!"
    },
    {
      "number": 3,
      "supportCardId": "s_card-3-0002",
      "text": "These guys are such a hassle..."
    },
    {
      "number": 1,
      "supportCardId": "s_card-3-0003",
      "text": "Alright! Makeup’s done!\nLet’s go out and have fun!"
    },
    {
      "number": 2,
      "supportCardId": "s_card-3-0003",
      "text": "Nope! Not good enough!\nStand up straight!"
    },
    {
      "number": 3,
      "supportCardId": "s_card-3-0003",
      "text": "I knew it, no good, ughhh!"
    },
    {
      "number": 1,
      "supportCardId": "s_card-3-0004",
      "text": "Grrr... Big Sis, I swear..."
    },
    {
      "number": 2,
      "supportCardId": "s_card-3-0004",
      "text": "I-I’ll never..."
    },
    {
      "number": 3,
      "supportCardId": "s_card-3-0004",
      "text": "N-Never lose!"
    },
    {
      "number": 1,
      "supportCardId": "s_card-3-0005",
      "text": "We’re already third-years now."
    },
    {
      "number": 2,
      "supportCardId": "s_card-3-0005",
      "text": "...Yeah. We need to make sure we don’t\nembarrass ourselves in front of the juniors."
    },
    {
      "number": 3,
      "supportCardId": "s_card-3-0005",
      "text": "We need to try even harder, huh?"
    },
    {
      "number": 1,
      "supportCardId": "s_card-3-0006",
      "text": "Ughhh... It’s never-ending~!"
    },
    {
      "number": 2,
      "supportCardId": "s_card-3-0006",
      "text": "Don’t worry, almost there."
    },
    {
      "number": 3,
      "supportCardId": "s_card-3-0006",
      "text": "Let’s push through together to the end!"
    },
    {
      "number": 1,
      "supportCardId": "s_card-3-0007",
      "text": "Do you need a drink?"
    },
    {
      "number": 2,
      "supportCardId": "s_card-3-0007",
      "text": "Oh, thank you...!"
    },
    {
      "number": 3,
      "supportCardId": "s_card-3-0007",
      "text": "(It’s like he’s a prince...!)"
    },
    {
      "number": 1,
      "supportCardId": "s_card-3-0008",
      "text": "Whoa, Lilja, look at that!"
    },
    {
      "number": 2,
      "supportCardId": "s_card-3-0008",
      "text": "What’s wrong, Sumika cha—"
    },
    {
      "number": 3,
      "supportCardId": "s_card-3-0008",
      "text": "Say cheese!"
    },
    {
      "number": 1,
      "supportCardId": "s_card-3-0009",
      "text": "Today’s the final chance."
    },
    {
      "number": 2,
      "supportCardId": "s_card-3-0009",
      "text": "I-I’ll make it succeed no matter what!"
    },
    {
      "number": 3,
      "supportCardId": "s_card-3-0009",
      "text": "Nngh... Alright, let’s do this!"
    },
    {
      "number": 1,
      "supportCardId": "s_card-3-0010",
      "text": "Who’s this?"
    },
    {
      "number": 2,
      "supportCardId": "s_card-3-0010",
      "text": "This is my treasure!\nI-Isn’t it adorable?"
    },
    {
      "number": 3,
      "supportCardId": "s_card-3-0010",
      "text": "Both the teddy bear and China are\nadorable!"
    },
    {
      "number": 1,
      "supportCardId": "s_card-3-0011",
      "text": "President, Misuzu-chan!\nWe came to visit!"
    },
    {
      "number": 2,
      "supportCardId": "s_card-3-0011",
      "text": "Oh my. Hehe, you’re lively as always."
    },
    {
      "number": 3,
      "supportCardId": "s_card-3-0011",
      "text": "Geez... The student council room isn’t\na playground."
    },
    {
      "number": 1,
      "supportCardId": "s_card-3-0012",
      "text": "(Phew... Time for a quick break...)"
    },
    {
      "number": 2,
      "supportCardId": "s_card-3-0012",
      "text": "Hahh... Not yet, not yet...!"
    },
    {
      "number": 3,
      "supportCardId": "s_card-3-0012",
      "text": "...Seriously."
    },
    {
      "number": 1,
      "supportCardId": "s_card-3-0013",
      "text": "Welcome—Ack!"
    },
    {
      "number": 2,
      "supportCardId": "s_card-3-0013",
      "text": "Fancy meeting you, Kotone."
    },
    {
      "number": 3,
      "supportCardId": "s_card-3-0013",
      "text": "(This person, even here?!)"
    },
    {
      "number": 1,
      "supportCardId": "s_card-3-0014",
      "text": "Still just the beginning, we’ve only just\nstarted!"
    },
    {
      "number": 2,
      "supportCardId": "s_card-3-0014",
      "text": "Let’s see some excitement so loud it\ndrowns out my voice!"
    },
    {
      "number": 3,
      "supportCardId": "s_card-3-0014",
      "text": "...So this is, the Prima Stella..."
    },
    {
      "number": 1,
      "supportCardId": "s_card-3-0015",
      "text": "Alright, let’s capture a photo fit for the\nnew student council!"
    },
    {
      "number": 2,
      "supportCardId": "s_card-3-0015",
      "text": "I-I’m not ready yettt!!"
    },
    {
      "number": 3,
      "supportCardId": "s_card-3-0015",
      "text": "...Yawn."
    },
    {
      "number": 1,
      "supportCardId": "s_card-3-0016",
      "text": "Got you, Hiro-chan~!"
    },
    {
      "number": 2,
      "supportCardId": "s_card-3-0016",
      "text": "Captured."
    },
    {
      "number": 3,
      "supportCardId": "s_card-3-0016",
      "text": "Hataya-san,\nplease keep up properly!"
    },
    {
      "number": 4,
      "supportCardId": "s_card-3-0016",
      "text": "...Alright, I give up."
    },
    {
      "number": 1,
      "supportCardId": "s_card-3-0017",
      "text": "Last box, let’s go!"
    },
    {
      "number": 2,
      "supportCardId": "s_card-3-0017",
      "text": "W-Wait...!\nIt’s heavy, be careful..."
    },
    {
      "number": 3,
      "supportCardId": "s_card-3-0017",
      "text": "It’s fine, it’s fine!"
    },
    {
      "number": 1,
      "supportCardId": "s_card-3-0018",
      "text": "Temari-chi～,\nyou’re not eating any snacks, are you?"
    },
    {
      "number": 2,
      "supportCardId": "s_card-3-0018",
      "text": "Are you on a diet or something?"
    },
    {
      "number": 3,
      "supportCardId": "s_card-3-0018",
      "text": "Grr... Shut up."
    },
    {
      "number": 1,
      "supportCardId": "s_card-3-0019",
      "text": "Hehe, it’s no trouble at all."
    },
    {
      "number": 2,
      "supportCardId": "s_card-3-0019",
      "text": "Feel free to rely on me anytime."
    },
    {
      "number": 3,
      "supportCardId": "s_card-3-0019",
      "text": "You’re my student, after all."
    },
    {
      "number": 1,
      "supportCardId": "s_card-3-0020",
      "text": "Oh, it’s an autumn flavors fair!\nI’m getting hungry just thinking about it."
    },
    {
      "number": 2,
      "supportCardId": "s_card-3-0020",
      "text": "Chestnut rice bento, rice balls...\nAnd let’s get some sweets too!"
    },
    {
      "number": 3,
      "supportCardId": "s_card-3-0020",
      "text": "Hehe... This kind of lunch is nice once\nin a while!"
    },
    {
      "number": 1,
      "supportCardId": "s_card-3-0021",
      "text": "Mari-chan, you’ll catch a cold!"
    },
    {
      "number": 2,
      "supportCardId": "s_card-3-0021",
      "text": "I-I know...!"
    },
    {
      "number": 3,
      "supportCardId": "s_card-3-0021",
      "text": "Throws me off balance... Geez..."
    },
    {
      "number": 1,
      "supportCardId": "s_card-3-0022",
      "text": "Oh! Mao-senpai, look, a rainbow!"
    },
    {
      "number": 2,
      "supportCardId": "s_card-3-0022",
      "text": "Ah, you’re right."
    },
    {
      "number": 3,
      "supportCardId": "s_card-3-0022",
      "text": "Hehe, maybe it’s a reward for cleaning?"
    },
    {
      "number": 1,
      "supportCardId": "s_card-3-0023",
      "text": "Oh, found a puddle!"
    },
    {
      "number": 2,
      "supportCardId": "s_card-3-0023",
      "text": "Ume, stop that!"
    },
    {
      "number": 3,
      "supportCardId": "s_card-3-0023",
      "text": "Cut it out!"
    },
    {
      "number": 1,
      "supportCardId": "s_card-3-0024",
      "text": "Agh...\nI don’t get it at all..."
    },
    {
      "number": 2,
      "supportCardId": "s_card-3-0024",
      "text": "Kotone! That’s not it, I told you!"
    },
    {
      "number": 3,
      "supportCardId": "s_card-3-0024",
      "text": "Reward... Tonkatsu... Zzz..."
    },
    {
      "number": 1,
      "supportCardId": "s_card-3-0025",
      "text": "We made it all the way here, huh..."
    },
    {
      "number": 2,
      "supportCardId": "s_card-3-0025",
      "text": "Hehe... So tired..."
    },
    {
      "number": 3,
      "supportCardId": "s_card-3-0025",
      "text": "Time for celebratory food!\nLet’s dig in!"
    },
    {
      "number": 1,
      "supportCardId": "s_card-3-0026",
      "text": "Cleaning the pool seemed like such a\ndrag..."
    },
    {
      "number": 2,
      "supportCardId": "s_card-3-0026",
      "text": "But doing it with Lilja was fun!"
    },
    {
      "number": 3,
      "supportCardId": "s_card-3-0026",
      "text": "...Yeah. I had fun too."
    },
    {
      "number": 1,
      "supportCardId": "s_card-3-0027",
      "text": "Alright, everyone!\nAfter grueling lessons, it’s—"
    },
    {
      "number": 2,
      "supportCardId": "s_card-3-0027",
      "text": "Time to enjoy a vacation~~♪"
    },
    {
      "number": 3,
      "supportCardId": "s_card-3-0027",
      "text": "Wooooooo!!"
    },
    {
      "number": 1,
      "supportCardId": "s_card-3-0028",
      "text": "How about a truce?"
    },
    {
      "number": 2,
      "supportCardId": "s_card-3-0028",
      "text": "Hmph,\ndo you think you can persuade me?"
    },
    {
      "number": 3,
      "supportCardId": "s_card-3-0028",
      "text": "...This back-and-forth feels nostalgic."
    },
    {
      "number": 1,
      "supportCardId": "s_card-3-0029",
      "text": "Alright, let’s surround them!"
    },
    {
      "number": 2,
      "supportCardId": "s_card-3-0029",
      "text": "Leave it to me, Kotone!"
    },
    {
      "number": 3,
      "supportCardId": "s_card-3-0029",
      "text": "We’re in sync only at times like this!"
    },
    {
      "number": 1,
      "supportCardId": "s_card-3-0030",
      "text": "What’s that over there?!"
    },
    {
      "number": 2,
      "supportCardId": "s_card-3-0030",
      "text": "Hehe~ China-chan,\nif you rush like that, you’ll get lost!"
    },
    {
      "number": 3,
      "supportCardId": "s_card-3-0030",
      "text": "It’s fine!\nI’m holding hands with Sis!"
    },
    {
      "number": 1,
      "supportCardId": "s_card-3-0031",
      "text": "Leave it to me. I’ll light it up for you."
    },
    {
      "number": 2,
      "supportCardId": "s_card-3-0031",
      "text": "Oh, thank you...!"
    },
    {
      "number": 3,
      "supportCardId": "s_card-3-0031",
      "text": "Hehe, sparklers are so fun."
    },
    {
      "number": 1,
      "supportCardId": "s_card-3-0032",
      "text": "Are you worried about Tsubame-chan?"
    },
    {
      "number": 2,
      "supportCardId": "s_card-3-0032",
      "text": "N-No, not at all.\nI was just deep in thought."
    },
    {
      "number": 3,
      "supportCardId": "s_card-3-0032",
      "text": "About the problem kids I scouted..."
    },
    {
      "number": 1,
      "supportCardId": "s_card-3-0034",
      "text": "How much longer until the laundry’s\ndone?"
    },
    {
      "number": 2,
      "supportCardId": "s_card-3-0034",
      "text": "Still a while, I think."
    },
    {
      "number": 3,
      "supportCardId": "s_card-3-0034",
      "text": "Then I’ll pour us some more tea!"
    },
    {
      "number": 1,
      "supportCardId": "s_card-3-0035",
      "text": "Is that book interesting?"
    },
    {
      "number": 2,
      "supportCardId": "s_card-3-0035",
      "text": "It’s so thrilling!"
    },
    {
      "number": 3,
      "supportCardId": "s_card-3-0035",
      "text": "Maybe I should give it a read."
    },
    {
      "number": 1,
      "supportCardId": "s_card-3-0036",
      "text": "Temari-chi, try this on!"
    },
    {
      "number": 2,
      "supportCardId": "s_card-3-0036",
      "text": "Absolutely not. Hey, don’t—"
    },
    {
      "number": 3,
      "supportCardId": "s_card-3-0036",
      "text": "Hehe, it suits you so well! Super cute~!"
    },
    {
      "number": 1,
      "supportCardId": "s_card-3-0037",
      "text": "Ahh~ It’s getting cooler!"
    },
    {
      "number": 2,
      "supportCardId": "s_card-3-0037",
      "text": "Autumn is for art, reading, and food!\nLet’s go enjoy some autumn flavors!"
    },
    {
      "number": 3,
      "supportCardId": "s_card-3-0037",
      "text": "It’s always fun with China.\nHehe, thank you for everything."
    },
    {
      "number": 1,
      "supportCardId": "s_card-3-0038",
      "text": "Rehearsal prep is ready."
    },
    {
      "number": 2,
      "supportCardId": "s_card-3-0038",
      "text": "Giving a speech to freshmen is a bit\nnerve-wracking."
    },
    {
      "number": 3,
      "supportCardId": "s_card-3-0038",
      "text": "Even you get nervous, President?\nThat’s surprising."
    },
    {
      "number": 1,
      "supportCardId": "s_card-3-0039",
      "text": "Oh, Kotone.\nI’ll go on ahead."
    },
    {
      "number": 2,
      "supportCardId": "s_card-3-0039",
      "text": "...W-Wasn’t that way too fast?!"
    },
    {
      "number": 3,
      "supportCardId": "s_card-3-0039",
      "text": "Hehe. Think you can keep up?"
    },
    {
      "number": 1,
      "supportCardId": "s_card-3-0040",
      "text": "Hehe~ It’s about time.\nThe timing is tricky, you know."
    },
    {
      "number": 2,
      "supportCardId": "s_card-3-0040",
      "text": "...What a nice smell.\nIt’s exciting..."
    },
    {
      "number": 3,
      "supportCardId": "s_card-3-0040",
      "text": "This side should be good to go.\nLilja, your turn."
    },
    {
      "number": 1,
      "supportCardId": "s_card-3-0041",
      "text": "Misuzu-chan!\nLet’s check over there too!"
    },
    {
      "number": 2,
      "supportCardId": "s_card-3-0041",
      "text": "Hehe, alright."
    },
    {
      "number": 3,
      "supportCardId": "s_card-3-0041",
      "text": "Now, now, don’t rush."
    },
    {
      "number": 1,
      "supportCardId": "s_card-3-0042",
      "text": "It’s snowing~."
    },
    {
      "number": 2,
      "supportCardId": "s_card-3-0042",
      "text": "The bus should come soon.\nIt’s getting a bit chilly, huh?"
    },
    {
      "number": 3,
      "supportCardId": "s_card-3-0042",
      "text": "Here, Lilja,\nI’ll share my scarf with you!"
    },
    {
      "number": 1,
      "supportCardId": "s_card-3-0043",
      "text": "Hehe~ Gotcha～♪\nNow I’m in the lead...!"
    },
    {
      "number": 2,
      "supportCardId": "s_card-3-0043",
      "text": "Wait up～!\nI won’t lose that easily!"
    },
    {
      "number": 3,
      "supportCardId": "s_card-3-0043",
      "text": "What?! You’re way too fast!!"
    },
    {
      "number": 1,
      "supportCardId": "s_card-3-0044",
      "text": "Good work, Temari-chi~.\nWant a sports drink?"
    },
    {
      "number": 2,
      "supportCardId": "s_card-3-0044",
      "text": "Lilja says she wants to try this part next."
    },
    {
      "number": 3,
      "supportCardId": "s_card-3-0044",
      "text": "Whoops! Sorry, I’m late~!"
    },
    {
      "number": 1,
      "supportCardId": "s_card-3-0045",
      "text": "Someday, we’ll surely—"
    },
    {
      "number": 2,
      "supportCardId": "s_card-3-0045",
      "text": "Perform this song on a big stage, right?!"
    },
    {
      "number": 3,
      "supportCardId": "s_card-3-0045",
      "text": "Hehe... There’s still a long way to go."
    },
    {
      "number": 1,
      "supportCardId": "s_card-3-0046",
      "text": "(This time, for sure—)"
    },
    {
      "number": 2,
      "supportCardId": "s_card-3-0046",
      "text": "(I’ll make it mine.)"
    },
    {
      "number": 3,
      "supportCardId": "s_card-3-0046",
      "text": "(The one who masters this song\nis the best... me!)"
    }
  ],
  "rules": {
    "primaryKeys": [
      "supportCardId",
      "number"
    ]
  }
}
